odoo_csv_tools/__init__.py
odoo_csv_tools/export_threaded.py
odoo_csv_tools/import_threaded.py
odoo_csv_tools/migrate.py
odoo_csv_tools/lib/__init__.py
odoo_csv_tools/lib/checker.py
odoo_csv_tools/lib/conf_lib.py
odoo_csv_tools/lib/mapper.py
odoo_csv_tools/lib/transform.py
odoo_csv_tools/lib/workflow.py
odoo_csv_tools/lib/internal/__init__.py
odoo_csv_tools/lib/internal/csv_reader.py
odoo_csv_tools/lib/internal/exceptions.py
odoo_csv_tools/lib/internal/io.py
odoo_csv_tools/lib/internal/rpc_thread.py
odoo_csv_tools/lib/internal/tools.py
odoo_import_export_client-3.0.0.data/scripts/odoo_convert_path_to_image.py
odoo_import_export_client-3.0.0.data/scripts/odoo_convert_url_to_image.py
odoo_import_export_client-3.0.0.data/scripts/odoo_export_thread.py
odoo_import_export_client-3.0.0.data/scripts/odoo_import_thread.py
odoo_import_export_client-3.0.0.dist-info/COPYING
odoo_import_export_client-3.0.0.dist-info/METADATA
odoo_import_export_client-3.0.0.dist-info/WHEEL
odoo_import_export_client-3.0.0.dist-info/top_level.txt
odoo_import_export_client-3.0.0.dist-info/RECORD
