Metadata-Version: 2.1
Name: odoo-import-export-client
Version: 3.0.0
Summary: Library and script that allow to export and import data to Odoo using rpc api.
Home-page: https://github.com/tfrancoi/odoo_csv_import
Author: Thibault Francois
Author-email: francois.th@gmail.com
License: LGPLv3
Keywords: odoo library import export thread python client lib web service
Platform: UNKNOWN
Classifier: License :: OSI Approved :: GNU Lesser General Public License v3 (LGPLv3)
Classifier: Programming Language :: Python
Requires-Dist: odoo-client-lib
Requires-Dist: future
Requires-Dist: unicodecsv
Requires-Dist: requests
